gilfoyle/__init__.py
gilfoyle/report.py
gilfoyle/assets/examples.html
gilfoyle/assets/template.html
gilfoyle/assets/css/default.css
gilfoyle/assets/data/ga-sample.csv
gilfoyle/assets/images/barchart.png
gilfoyle/assets/images/cover.jpg
gilfoyle/assets/templates/chapter.tmpl
gilfoyle/assets/templates/cover.tmpl
gilfoyle/assets/templates/message.tmpl
gilfoyle/assets/templates/metrics.tmpl
gilfoyle/assets/templates/notification.tmpl
gilfoyle/assets/templates/report.tmpl
gilfoyle_forked-1.2.0.dist-info/LICENSE
gilfoyle_forked-1.2.0.dist-info/METADATA
gilfoyle_forked-1.2.0.dist-info/WHEEL
gilfoyle_forked-1.2.0.dist-info/top_level.txt
gilfoyle_forked-1.2.0.dist-info/RECORD
