Metadata-Version: 2.1
Name: gilfoyle-forked
Version: 1.2.0
Summary: Gilfoyle is a Python-based report generator for data scientists who use Pandas.
Home-page: https://github.com/sr-auto/gilfoyle
Download-URL: https://github.com/sr-auto/gilfoyle/archive/master.zip
Author: Shahab Rashid
Author-email: sr.python10@gmail.com
License: MIT
Keywords: python,reports,reporting,pandas,pdf
Classifier: Development Status :: 3 - Alpha
Classifier: Intended Audience :: Developers
Classifier: Topic :: Software Development :: Libraries :: Python Modules
Classifier: License :: OSI Approved :: MIT License
Classifier: Programming Language :: Python :: 3.8
License-File: LICENSE
Requires-Dist: pandas
Requires-Dist: weasyprint
Requires-Dist: jinja2
Requires-Dist: seaborn
